{
    "repos_to_ensure": {	
	"1001": {
	    comment: "COMMENTED OUT: ubuntu-server 14.04 trusty cdrom",
	    context: "ubuntu_14_4",
	    url: "cdrom:[Ubuntu-Server 14.04.3 LTS _Trusty Tahr_ - Release amd64 (20150805)]/",
	    distribution: "trusty",
	    components: [ "main", "restricted" ],
	    types: [ "# deb" ],
	},
	"1101": {
	    comment: "ubuntu 14.04 trusty standard repository",
	    context: "ubuntu_14_4",
	    url: "http://us.archive.ubuntu.com/ubuntu/",
	    distribution: "trusty",
	    components: [ "main", "restricted",  ],
	    types: [ "deb", "deb-src" ],
	},
	"1102": {
	    comment: "ubuntu 14.04 trusty security repository",
	    context: "ubuntu_14_4",
	    url: "http://security.ubuntu.com/ubuntu",
	    distribution: "trusty-security",
	    components: [ "main", "restricted",  ],
	    types: [ "deb", "# deb-src" ],
	},
	"1103": {
	    comment: "ubuntu 14.04 trusty updates repository",
	    context: "ubuntu_14_4",
	    url: "http://us.archive.ubuntu.com/ubuntu/",
	    distribution: "trusty-updates",
	    components: [ "main", "restricted" ],
	    types: [ "deb", "deb-src" ],
	},
	"1104": {
	    comment: "ubuntu 14.04 trusty universe and multiverse repositories - not fully supported by ubuntu team",
	    context: "ubuntu_14_4",
	    url: "http://us.archive.ubuntu.com/ubuntu/",
	    distribution: "trusty",
	    components: [ "universe", "multiverse" ],
	    types: [ "deb", "# deb-src" ],
	},
	"1105": {
	    comment: "ubuntu 14.04 trusty universe and multiverse update repositories - not fully supported by ubuntu team",
	    context: "ubuntu_14_4",
	    url: "http://us.archive.ubuntu.com/ubuntu/",
	    distribution: "trusty-updates",
	    components: [ "universe", "multiverse" ],
	    types: [ "deb", "# deb-src" ],
	},
	"1106": {
	    comment: "ubuntu 14.04 trusty universe and multiverse security repositories - not fully supported by ubuntu team",
	    context: "ubuntu_14_4",
	    url: "http://us.archive.ubuntu.com/ubuntu/",
	    distribution: "trusty-security",
	    components: [ "universe", "multiverse" ],
	    types: [ "deb", "# deb-src" ],
	},
	"1107": {
	    comment: "ubuntu 14.04 trusty all backports repositories - not fully supported by ubuntu team",
	    context: "ubuntu_14_4",
	    url: "http://us.archive.ubuntu.com/ubuntu/",
	    distribution: "trusty-backports",
	    components: [ "main", "restricted", "universe", "multiverse" ],
	    types: [ "deb", "# deb-src" ],
	},
	"1108": {
	    comment: "COMMENTED OUT: ubuntu 16.04 trusty partner repository - not part of ubuntu",
	    context: "ubuntu_14_4",
	    url: "http://archive.canonical.com/ubuntu",
	    distribution: "trusty",
	    components: [ "partner" ],
	    types: [ "# deb", "# deb-src" ],
	},
	
	"2001": {
	    comment: "COMMENTED OUT: ubuntu-server 16.04 xenial cdrom",
	    context: "ubuntu_16_4",
	    url: "cdrom:[Ubuntu-Server 16.04.1 LTS _Xenial Xerus_ - Release amd64 (20160719)]/",
	    distribution: "xenial",
	    components: [ "main", "restricted" ],
	    types: [ "# deb" ],
	},
	"2101": {
	    comment: "ubuntu 16.04 xenial standard repository",
	    context: "ubuntu_16_4",
	    url: "http://us.archive.ubuntu.com/ubuntu/",
	    distribution: "xenial",
	    components: [ "main", "restricted",  ],
	    types: [ "deb", "# deb-src" ],
	},
	"2102": {
	    comment: "ubuntu 16.04 xenial security repository",
	    context: "ubuntu_16_4",
	    url: "http://security.ubuntu.com/ubuntu",
	    distribution: "xenial-security",
	    components: [ "main", "restricted",  ],
	    types: [ "deb", "# deb-src" ],
	},
	"2103": {
	    comment: "ubuntu 16.04 xenial updates repository",
	    context: "ubuntu_16_4",
	    url: "http://us.archive.ubuntu.com/ubuntu/",
	    distribution: "xenial-updates",
	    components: [ "main", "restricted" ],
	    types: [ "deb", "# deb-src" ],
	},
	"2104": {
	    comment: "ubuntu 16.04 xenial universe and multiverse repositories - not fully supported by ubuntu team",
	    context: "ubuntu_16_4",
	    url: "http://us.archive.ubuntu.com/ubuntu/",
	    distribution: "xenial",
	    components: [ "universe", "multiverse" ],
	    types: [ "deb", "# deb-src" ],
	},
	"2105": {
	    comment: "ubuntu 16.04 xenial universe and multiverse update repositories - not fully supported by ubuntu team",
	    context: "ubuntu_16_4",
	    url: "http://us.archive.ubuntu.com/ubuntu/",
	    distribution: "xenial-updates",
	    components: [ "universe", "multiverse" ],
	    types: [ "deb", "# deb-src" ],
	},
	"2106": {
	    comment: "ubuntu 16.04 xenial universe and multiverse security repositories - not fully supported by ubuntu team",
	    context: "ubuntu_16_4",
	    url: "http://us.archive.ubuntu.com/ubuntu/",
	    distribution: "xenial-security",
	    components: [ "universe", "multiverse" ],
	    types: [ "deb", "# deb-src" ],
	},
	"2107": {
	    comment: "ubuntu 16.04 xenial all backports repositories - not fully supported by ubuntu team",
	    context: "ubuntu_16_4",
	    url: "http://us.archive.ubuntu.com/ubuntu/",
	    distribution: "xenial-backports",
	    components: [ "main", "restricted", "universe", "multiverse" ],
	    types: [ "deb", "# deb-src" ],
	},
	"2108": {
	    comment: "COMMENTED OUT: ubuntu 16.04 xenial partner repository - not part of ubuntu",
	    context: "ubuntu_16_4",
	    url: "http://archive.canonical.com/ubuntu",
	    distribution: "xenial",
	    components: [ "partner" ],
	    types: [ "# deb", "# deb-src" ],
	},
	
	"5101": {
	    comment: "ubuntu 16.04 xenial umake repository for development installations",
	    context: "ubuntu_make",
	    url: "http://ppa.launchpad.net/ubuntu-desktop/ubuntu-make/ubuntu",
	    distribution: "xenial",
	    components: [ "main" ],
	    types: [ "deb", "deb-src" ],
	    keyfile: "ubuntu_make.txt",
	    keyfile_fingerprint: "399B 698E EA9E F163 B6F9  A0F6 2CC9 8497 A123 1595",
	},

    	"8101": {
	    comment: "External network WSU VTW10 Tom Wallis debian repository",
	    context: "debian, !subnet_cs_blue, !subnet_cs_pink",
	    url: "http://baley-ext.cs.wichita.edu/wsu/",
	    distribution: "debian-wsu-local10",
	    components: [ "main" ],
	    types: [ "deb" ],
	    keyfile: "debian_wsu_local.txt",
	    keyfile_fingerprint: "C454 80EB B31E 8487 DC98  09E7 3077 B433 E194 1965",
	},
    	"8102": {
	    comment: "bluenet WSU VTW10 Tom Wallis debian repository",
	    context: "debian, subnet_cs_blue",
	    url: "http://baley-blue.cs.wichita.edu/wsu/",
	    distribution: "debian-wsu-local10",
	    components: [ "main" ],
	    types: [ "deb" ],
	    keyfile: "debian_wsu_local.txt",
	    keyfile_fingerprint: "C454 80EB B31E 8487 DC98  09E7 3077 B433 E194 1965",
	},
    	"8103": {
	    comment: "pinknet WSU VTW10 Tom Wallis debian repository",
	    context: "debian, subnet_cs_pink",
	    url: "http://baley-pink.cs.wichita.edu/wsu/",
	    distribution: "debian-wsu-local10",
	    components: [ "main" ],
	    types: [ "deb" ],
	    keyfile: "debian_wsu_local.txt",
	    keyfile_fingerprint: "C454 80EB B31E 8487 DC98  09E7 3077 B433 E194 1965",
	},
    	"9101": {
	    comment: "NOT USED: cfengine debian repository on amazonaws, added as file in sources.list.d",
	    context: "NOT_debian",
	    url: "https://cfengine-package-repos.s3.amazonaws.com/pub/apt/packages",
	    distribution: "stable",
	    components: [ "main", ],
	    types: [ "deb", ],
	},
    },
    
    "repos_to_wipe": {
    },
}
